mindpandas/__init__.py
mindpandas/_version.py
mindpandas/channel.py
mindpandas/cli.py
mindpandas/config.py
mindpandas/dataframe.py
mindpandas/general.py
mindpandas/groupby.py
mindpandas/index.py
mindpandas/internal_config.py
mindpandas/io.py
mindpandas/iterator.py
mindpandas/series.py
mindpandas/util.py
mindpandas/backend/__init__.py
mindpandas/backend/base_frame.py
mindpandas/backend/base_general.py
mindpandas/backend/base_io.py
mindpandas/backend/eager/__init__.py
mindpandas/backend/eager/ds_partition.py
mindpandas/backend/eager/eager_backend.py
mindpandas/backend/eager/eager_frame.py
mindpandas/backend/eager/eager_general.py
mindpandas/backend/eager/eager_io.py
mindpandas/backend/eager/multiprocess_operators.py
mindpandas/backend/eager/multithread_operators.py
mindpandas/backend/eager/partition.py
mindpandas/backend/eager/partition_operators.py
mindpandas/backend/eager/yr/__init__.py
mindpandas/backend/eager/yr/yr_remote_functions.py
mindpandas/backend/eager/yr/yr_scheduler.py
mindpandas/compiler/__init__.py
mindpandas/compiler/function_factory.py
mindpandas/compiler/pandas_factory.py
mindpandas/compiler/query_compiler.py
mindpandas/dist_executor/__init__.py
mindpandas/dist_executor/modules/__init__.py
mindpandas/dist_executor/modules/basic/config.xml
mindpandas/dist_executor/modules/basic/deploy.sh
mindpandas/dist_executor/modules/basic/utils.sh
mindpandas/dist_executor/modules/basic/bin/etcd/etcd
mindpandas/dist_executor/modules/basic/bin/etcd/etcdctl
mindpandas/dist_executor/modules/basic/bin/redis/redis-server
mindpandas/dist_executor/modules/basic/config/redis/redis.conf
mindpandas/dist_executor/modules/bin/config.sh
mindpandas/dist_executor/modules/bin/distribute-executor
mindpandas/dist_executor/modules/bin/encrypt
mindpandas/dist_executor/modules/bin/health-check
mindpandas/dist_executor/modules/bin/health_check.py
mindpandas/dist_executor/modules/bin/monitor.sh
mindpandas/dist_executor/modules/bin/mpctl
mindpandas/dist_executor/modules/bin/start_mp
mindpandas-0.2.0.dist-info/LICENSE
mindpandas-0.2.0.dist-info/METADATA
mindpandas-0.2.0.dist-info/NOTICE
mindpandas-0.2.0.dist-info/WHEEL
mindpandas-0.2.0.dist-info/entry_points.txt
mindpandas-0.2.0.dist-info/top_level.txt
mindpandas-0.2.0.dist-info/RECORD
