Metadata-Version: 2.1
Name: mindpandas
Version: 0.2.0
Summary: mindpandas platform: linux, cpu: x86_64, git version: [sha1]:e07dbf1, [branch]: (HEAD -> master, origin/master, origin/HEAD)
Home-page: https://www.mindspore.cn
Download-URL: https://gitee.com/mindspore/mindpandas/tags
Author: The MindSpore Authors
Author-email: contact@mindspore.cn
License: Apache 2.0
Project-URL: Sources, https://gitee.com/mindspore/mindpandas
Project-URL: Issue Tracker, https://gitee.com/mindspore/mindpandas/issues
Keywords: mindpandas
Platform: linux
Requires-Python: >=3.7, <3.10
License-File: LICENSE
License-File: NOTICE
Requires-Dist: pandas (==1.3.5)
Requires-Dist: numpy (>=1.19.5)
Requires-Dist: click (>=7.0)
Requires-Dist: pycryptodomex (==3.11.0)
Requires-Dist: cloudpickle (==1.3.0)
Requires-Dist: msgpack (==1.0.0)
Requires-Dist: urllib3 (==1.26.5)
Requires-Dist: grpcio (==1.41.0)
Requires-Dist: uvloop (==0.16.0)
Requires-Dist: protobuf (==3.19.3)
Requires-Dist: psutil (>=5.7.0)
